{
	"mfe-alarm": "http://localhost:8080/mfealarm/remoteEntry.js",
	"mfe-notification": "http://localhost:8080/remoteEntry.js",
	"mfe-analytics-dashboard": "http://localhost:8080/remoteEntry.js",
	"user-management-mfe": "http://localhost:8080/user-management-mfe/remoteEntry.js",
	"historian-viewer": "http://localhost:8080/mfe-historian/remoteEntry.js",
	"mfe-trends": "http://localhost:8080/mfe-trends/remoteEntry.js",
	"mfe-custom-dashboard": "http://localhost:8080/mfe-custom-dashboard/remoteEntry.js"
}